cliptext/__init__.py
cliptext/core.py
cliptext-0.1.1.dist-info/METADATA
cliptext-0.1.1.dist-info/WHEEL
cliptext-0.1.1.dist-info/top_level.txt
cliptext-0.1.1.dist-info/RECORD
