Metadata-Version: 2.4
Name: cliptext
Version: 0.1.1
Summary: Smart sentence-based text clipper that respects meaning and punctuation.
Author-email: Vivek Appu <your-email@example.com>
License: MIT
Project-URL: Homepage, https://github.com/yourusername/cliptext
Keywords: text,clip,sentence,truncate,youtube,seo
Requires-Python: >=3.7
